pyphidgets/__init__.py
pyphidgets-0.1.dist-info/DESCRIPTION.rst
pyphidgets-0.1.dist-info/METADATA
pyphidgets-0.1.dist-info/RECORD
pyphidgets-0.1.dist-info/WHEEL
pyphidgets-0.1.dist-info/metadata.json
pyphidgets-0.1.dist-info/top_level.txt
