Metadata-Version: 2.0
Name: pyphidgets
Version: 0.1
Summary: cross-platform Python API
Home-page: https://github.com/scivision/phidgets-servo-c-python
Author: UNKNOWN
Author-email: UNKNOWN
License: UNKNOWN
Platform: UNKNOWN
Classifier: Development Status :: 2 - Pre-Alpha
Classifier: License :: OSI Approved :: MIT License
Classifier: Programming Language :: Python
